README.md
setup.cfg
setup.py
diff_dd/__init__.py
diff_dd/module.py
diff_dd.egg-info/PKG-INFO
diff_dd.egg-info/SOURCES.txt
diff_dd.egg-info/dependency_links.txt
diff_dd.egg-info/entry_points.txt
diff_dd.egg-info/top_level.txt