Metadata-Version: 1.1
Name: diff-dd
Version: 1.0.4
Summary: Diff Disk Dump
Home-page: https://github.com/larrabee/diff-dd
Author: larrabee
Author-email: kafatron@gmail.com
License: GPLv3
Keywords: diff-dd diff disk dump tool
Platform: UNKNOWN
Classifier: Development Status :: 5 - Production/Stable
Classifier: Environment :: Console
Classifier: Intended Audience :: System Administrators
Classifier: Operating System :: POSIX :: Linux
Classifier: Operating System :: Unix
Classifier: Topic :: Utilities
Classifier: Topic :: System :: Archiving :: Backup
Classifier: License :: OSI Approved :: GNU General Public License v3 (GPLv3)
Classifier: Programming Language :: Python :: 3
Classifier: Programming Language :: Python :: 2.7
